python2verilog/__init__.py
python2verilog/__main__.py
python2verilog/py.typed
python2verilog/api/__init__.py
python2verilog/api/context.py
python2verilog/api/exit_handler.py
python2verilog/api/file_namespaces.py
python2verilog/api/modes.py
python2verilog/api/namespace.py
python2verilog/api/python.py
python2verilog/api/verilogify.py
python2verilog/backend/__init__.py
python2verilog/backend/verilog/__init__.py
python2verilog/backend/verilog/ast.py
python2verilog/backend/verilog/codegen.py
python2verilog/backend/verilog/config.py
python2verilog/backend/verilog/fsm.py
python2verilog/backend/verilog/module.py
python2verilog/backend/verilog/testbench.py
python2verilog/exceptions/__init__.py
python2verilog/frontend/__init__.py
python2verilog/frontend/function.py
python2verilog/ir/__init__.py
python2verilog/ir/context.py
python2verilog/ir/expressions.py
python2verilog/ir/graph.py
python2verilog/ir/instance.py
python2verilog/ir/signals.py
python2verilog/optimizer/__init__.py
python2verilog/optimizer/helpers.py
python2verilog/optimizer/increase_work.py
python2verilog/simulation/__init__.py
python2verilog/simulation/display.py
python2verilog/simulation/iverilog.py
python2verilog/utils/__init__.py
python2verilog/utils/cytoscape.py
python2verilog/utils/decorator.py
python2verilog/utils/env.py
python2verilog/utils/fifo.py
python2verilog/utils/generics.py
python2verilog/utils/lines.py
python2verilog/utils/mit_license.py
python2verilog/utils/peek_counter.py
python2verilog/utils/typed.py
python2verilog/utils/visualization.py
python2verilog-0.5.0.dist-info/LICENSE
python2verilog-0.5.0.dist-info/METADATA
python2verilog-0.5.0.dist-info/WHEEL
python2verilog-0.5.0.dist-info/top_level.txt
python2verilog-0.5.0.dist-info/RECORD
