Metadata-Version: 2.1
Name: python2verilog
Version: 0.5.0
Summary: Converts a subset of python generator functions into synthesizable sequential SystemVerilog
Author-email: Kerry Wang <kerrywang369@gmail.com>
Project-URL: Homepage, https://github.com/WorldofKerry/ToHDL/
Project-URL: Bug Tracker, https://github.com/WorldofKerry/ToHDL/issues
Classifier: Programming Language :: Python :: 3
Classifier: License :: OSI Approved :: GNU General Public License v3 (GPLv3)
Requires-Python: >=3.9
License-File: LICENSE
Requires-Dist: typing-extensions
Requires-Dist: pytohdl
Provides-Extra: dev
Requires-Dist: maturin ; extra == 'dev'
Requires-Dist: pytest ; extra == 'dev'
Requires-Dist: pytest-cov ; extra == 'dev'
Requires-Dist: pytest-subtests ; extra == 'dev'
Requires-Dist: pandas ; extra == 'dev'
Requires-Dist: tabulate ; extra == 'dev'
Requires-Dist: matplotlib ; extra == 'dev'
Requires-Dist: networkx[default] ; extra == 'dev'
Requires-Dist: dash-cytoscape ; extra == 'dev'
Requires-Dist: dash ; extra == 'dev'
Requires-Dist: parameterized ; extra == 'dev'
Requires-Dist: pylint ; extra == 'dev'
Requires-Dist: mypy ; extra == 'dev'
Provides-Extra: full
Requires-Dist: matplotlib ; extra == 'full'
Requires-Dist: numpy ; extra == 'full'
Requires-Dist: dash-cytoscape ; extra == 'full'
Requires-Dist: dash ; extra == 'full'
